README.md
pcrypt.py
setup.py
pcrypt.egg-info/PKG-INFO
pcrypt.egg-info/SOURCES.txt
pcrypt.egg-info/dependency_links.txt
pcrypt.egg-info/entry_points.txt
pcrypt.egg-info/requires.txt
pcrypt.egg-info/top_level.txt