Metadata-Version: 2.1
Name: pcrypt
Version: 1.0.5
Summary: Pure-python implementation of the SHA2 crypt(3) functions
Home-page: https://github.com/thusoy/python-crypt
Author: Tarjei Husøy
Author-email: git@thusoy.com
License: MIT
Platform: UNKNOWN
Classifier: Development Status :: 5 - Production/Stable
Classifier: Intended Audience :: System Administrators
Classifier: License :: OSI Approved :: MIT License
Classifier: Programming Language :: Python :: 2.6
Classifier: Programming Language :: Python :: 2.7
Classifier: Programming Language :: Python :: 3.3
Classifier: Programming Language :: Python :: 3.4
Classifier: Programming Language :: Python :: 3.5
Classifier: Programming Language :: Python :: 3.6
Classifier: Programming Language :: Python :: 3.7
Provides-Extra: test
